floodgb/__init__.py
floodgb/utils.py
floodgb/v1.py
floodgb/v2.py
floodgb-0.1.6.dist-info/METADATA
floodgb-0.1.6.dist-info/WHEEL
floodgb-0.1.6.dist-info/licenses/LICENSE
floodgb-0.1.6.dist-info/RECORD
