Metadata-Version: 2.4
Name: floodgb
Version: 0.1.6
Summary: A flood model
Author-email: Mike Kittridge <mullenkamp1@gmail.com>
License-Expression: Apache-2.0
License-File: LICENSE
Keywords: flood,water
Classifier: Development Status :: 3 - Alpha
Classifier: Intended Audience :: Developers
Classifier: License :: OSI Approved :: Apache Software License
Classifier: Programming Language :: Python :: 3.8
Classifier: Programming Language :: Python :: 3.9
Requires-Python: >=3.9
Requires-Dist: booklet
Requires-Dist: matplotlib
Requires-Dist: numpy
Requires-Dist: orjson
Requires-Dist: pandas<2
Requires-Dist: scikit-learn>=1.3.1
Requires-Dist: scipy
Requires-Dist: xarray
Provides-Extra: dev
Requires-Dist: coverage[toml]>=6.5; extra == 'dev'
Requires-Dist: matplotlib; extra == 'dev'
Requires-Dist: pytest; extra == 'dev'
Requires-Dist: spyder-kernels==2.4; extra == 'dev'
